nsfw/__init__.py
nsfw/nsfw.py
sfw/__init__.py
sfw/sfw.py
actioncord-0.1.0.dist-info/LICENSE
actioncord-0.1.0.dist-info/METADATA
actioncord-0.1.0.dist-info/WHEEL
actioncord-0.1.0.dist-info/top_level.txt
actioncord-0.1.0.dist-info/RECORD
