Metadata-Version: 2.1
Name: actioncord
Version: 0.1.0
Summary: API wrapper for different actions, return their GIF urls. Made for Discord Embeds.
Home-page: https://github.com/pypa/sampleproject
Author: Parth Mishra
Author-email: halfstackpgr@gmail.com
Project-URL: Bug Tracker, https://github.com/pypa/sampleproject/issues
Classifier: Programming Language :: Python :: 3
Classifier: License :: OSI Approved :: MIT License
Classifier: Operating System :: OS Independent
Requires-Python: >=3.6
License-File: LICENSE
